rupi/__init__.py
rupi/chess_game.py
rupi/flames.py
rupi/xo.py
rupi-0.1.30.dist-info/LICENSE
rupi-0.1.30.dist-info/METADATA
rupi-0.1.30.dist-info/WHEEL
rupi-0.1.30.dist-info/top_level.txt
rupi-0.1.30.dist-info/RECORD
