Metadata-Version: 2.1
Name: rupi
Version: 0.1.30
Summary: A fun Python library with games like FLAMES, XO, and Chess.
Home-page: https://github.com/TanujairamV/rupi
Author: Tanujairam
Author-email: tanujairam.v@gmail.com
License: MIT
Project-URL: Documentation, https://github.com/TanujairamV/rupi/wiki
Project-URL: Bug Tracker, https://github.com/TanujairamV/rupi/issues
Project-URL: Source Code, https://github.com/TanujairamV/rupi
Keywords: games,python library,flames,xo,chess,tkinter
Classifier: Programming Language :: Python :: 3
Classifier: License :: OSI Approved :: MIT License
Classifier: Operating System :: OS Independent
Classifier: Intended Audience :: Developers
Classifier: Intended Audience :: Education
Classifier: Natural Language :: English
Classifier: Programming Language :: Python :: 3 :: Only
Requires-Python: >=3.6
License-File: LICENSE
Requires-Dist: requests>=2.20.0
Requires-Dist: chess>=1.9
Requires-Dist: tkintertable>=1.3.2
